tests/__init__.py
tests/test_validator.py
vin_validator/__init__.py
vin_validator/validator.py
vin_validator-0.2.dist-info/LICENSE
vin_validator-0.2.dist-info/METADATA
vin_validator-0.2.dist-info/WHEEL
vin_validator-0.2.dist-info/top_level.txt
vin_validator-0.2.dist-info/RECORD
