Metadata-Version: 2.1
Name: vin-validator
Version: 0.2
Summary: A package to validate Vehicle Identification Numbers (VINs)
Home-page: https://github.com/tlieshoff/vin-validator
Author: Tobias Lieshoff
Author-email: me@tobias-lieshoff.de
Classifier: Programming Language :: Python :: 3
Classifier: License :: OSI Approved :: MIT License
Classifier: Operating System :: OS Independent
Requires-Python: >=3.6
License-File: LICENSE
Requires-Dist: requests
